[{"label": "diningtable", "confidence": 0.56, "topleft": {"x": 101, "y": 168}, "bottomright": {"x": 477, "y": 374}}, {"label": "person", "confidence": 0.69, "topleft": {"x": 131, "y": 86}, "bottomright": {"x": 220, "y": 164}}, {"label": "person", "confidence": 0.68, "topleft": {"x": 244, "y": 90}, "bottomright": {"x": 337, "y": 175}}, {"label": "person", "confidence": 0.53, "topleft": {"x": 382, "y": 96}, "bottomright": {"x": 488, "y": 279}}, {"label": "person", "confidence": 0.79, "topleft": {"x": 0, "y": 132}, "bottomright": {"x": 126, "y": 371}}]