[{"label": "person", "confidence": 0.54, "topleft": {"x": 171, "y": 239}, "bottomright": {"x": 194, "y": 305}}, {"label": "person", "confidence": 0.79, "topleft": {"x": 228, "y": 219}, "bottomright": {"x": 263, "y": 335}}, {"label": "person", "confidence": 0.53, "topleft": {"x": 392, "y": 225}, "bottomright": {"x": 429, "y": 322}}, {"label": "person", "confidence": 0.78, "topleft": {"x": 382, "y": 234}, "bottomright": {"x": 412, "y": 311}}, {"label": "person", "confidence": 0.59, "topleft": {"x": 447, "y": 239}, "bottomright": {"x": 470, "y": 293}}]